akpub/__init__.py
akpub/publisher.py
akpub-0.1.0.dist-info/METADATA
akpub-0.1.0.dist-info/WHEEL
akpub-0.1.0.dist-info/top_level.txt
akpub-0.1.0.dist-info/RECORD
