Metadata-Version: 2.4
Name: akpub
Version: 0.1.0
Summary: A generic ROS2 publisher for numbers, strings, images, and video.
Author: akshay
Author-email: you@example.com
Requires-Python: >=3.6
Requires-Dist: setuptools
Requires-Dist: cv_bridge
Dynamic: author
Dynamic: author-email
Dynamic: description
Dynamic: description-content-type
Dynamic: requires-dist
Dynamic: requires-python
Dynamic: summary
